{
    "moves": [],
    "whiteTurn": true,
    "bcaptured": [],
    "wcaptured": [],
    "board": [
        "bR",
        "bk",
        "bB",
        "bQ",
        "bK",
        "bB",
        "bk",
        "bR",
        "bP",
        "bP",
        "bP",
        "bP",
        "bP",
        "bP",
        "bP",
        "bP",
        "__",
        "__",
        "__",
        "__",
        "__",
        "__",
        "__",
        "__",
        "__",
        "__",
        "__",
        "__",
        "__",
        "__",
        "__",
        "__",
        "__",
        "__",
        "__",
        "__",
        "__",
        "__",
        "__",
        "__",
        "__",
        "__",
        "__",
        "__",
        "__",
        "__",
        "__",
        "__",
        "wP",
        "wP",
        "wP",
        "wP",
        "wP",
        "wP",
        "wP",
        "wP",
        "wR",
        "wk",
        "wB",
        "wQ",
        "wK",
        "wB",
        "wk",
        "wR"
    ]
}